type_casting/__init__.py
type_casting/_common/__init__.py
type_casting/latest/__init__.py
type_casting/py37/__init__.py
type_casting/py38/__init__.py
type_casting/py39/__init__.py
type_casting-0.15.0.dist-info/LICENSE.txt
type_casting-0.15.0.dist-info/METADATA
type_casting-0.15.0.dist-info/WHEEL
type_casting-0.15.0.dist-info/top_level.txt
type_casting-0.15.0.dist-info/zip-safe
type_casting-0.15.0.dist-info/RECORD
