Metadata-Version: 2.1
Name: type-casting
Version: 0.15.0
Summary: Type Casting
Home-page: https://github.com/kshramt/type_casting
Author: kshramt
Classifier: License :: OSI Approved :: GNU General Public License v3 (GPLv3)
License-File: LICENSE.txt
Provides-Extra: dev
Requires-Dist: black ; extra == 'dev'
Requires-Dist: build ; extra == 'dev'
Requires-Dist: coverage ; extra == 'dev'
Requires-Dist: mypy ; extra == 'dev'
Requires-Dist: pyflakes ; extra == 'dev'
Requires-Dist: pylint ; extra == 'dev'
Requires-Dist: pytype ; extra == 'dev'
Requires-Dist: twine ; extra == 'dev'
